Flask_Humanoid-1.0.dist-info/DESCRIPTION.rst
Flask_Humanoid-1.0.dist-info/METADATA
Flask_Humanoid-1.0.dist-info/RECORD
Flask_Humanoid-1.0.dist-info/WHEEL
Flask_Humanoid-1.0.dist-info/metadata.json
Flask_Humanoid-1.0.dist-info/top_level.txt
flask_humanoid/__init__.py
flask_humanoid/compat.py
